<<<<<<< HEAD
Classfile /home/hoover/u3/dscarafo/Documents/fall2013/csc254/CSC254_A4/java/Class2.class
  Last modified Nov 5, 2013; size 442 bytes
  MD5 checksum c766e4135a39b6372558172824f065b7
=======
Classfile /home/hoover/u3/clehner/2013f/csc254/a4/java/Class2.class
  Last modified Nov 6, 2013; size 480 bytes
  MD5 checksum ff5273e774f7f90199a290774663e779
>>>>>>> 9852d261f5770e485a142b747224e91b3ac2926d
  Compiled from "Class2.java"
public class Class2
  SourceFile: "Class2.java"
  minor version: 0
  major version: 51
  flags: ACC_PUBLIC, ACC_SUPER
Constant pool:
<<<<<<< HEAD
   #1 = Methodref          #6.#17         //  java/lang/Object."<init>":()V
   #2 = Fieldref           #5.#18         //  Class2.info:Ljava/lang/String;
   #3 = Fieldref           #19.#20        //  java/lang/System.out:Ljava/io/PrintStream;
   #4 = Methodref          #21.#22        //  java/io/PrintStream.println:(Ljava/lang/String;)V
   #5 = Class              #23            //  Class2
   #6 = Class              #24            //  java/lang/Object
   #7 = Utf8               info
   #8 = Utf8               Ljava/lang/String;
   #9 = Utf8               <init>
  #10 = Utf8               (Ljava/lang/String;)V
  #11 = Utf8               Code
  #12 = Utf8               LineNumberTable
  #13 = Utf8               print_info
  #14 = Utf8               ()V
  #15 = Utf8               SourceFile
  #16 = Utf8               Class2.java
  #17 = NameAndType        #9:#14         //  "<init>":()V
  #18 = NameAndType        #7:#8          //  info:Ljava/lang/String;
  #19 = Class              #25            //  java/lang/System
  #20 = NameAndType        #26:#27        //  out:Ljava/io/PrintStream;
  #21 = Class              #28            //  java/io/PrintStream
  #22 = NameAndType        #29:#10        //  println:(Ljava/lang/String;)V
  #23 = Utf8               Class2
  #24 = Utf8               java/lang/Object
  #25 = Utf8               java/lang/System
  #26 = Utf8               out
  #27 = Utf8               Ljava/io/PrintStream;
  #28 = Utf8               java/io/PrintStream
  #29 = Utf8               println
=======
   #1 = Methodref          #7.#18         //  java/lang/Object."<init>":()V
   #2 = Fieldref           #6.#19         //  Class2.info:Ljava/lang/String;
   #3 = Fieldref           #20.#21        //  java/lang/System.out:Ljava/io/PrintStream;
   #4 = Methodref          #22.#23        //  java/io/PrintStream.println:(Ljava/lang/String;)V
   #5 = String             #24            //   /* not a comment */
   #6 = Class              #25            //  Class2
   #7 = Class              #26            //  java/lang/Object
   #8 = Utf8               info
   #9 = Utf8               Ljava/lang/String;
  #10 = Utf8               <init>
  #11 = Utf8               (Ljava/lang/String;)V
  #12 = Utf8               Code
  #13 = Utf8               LineNumberTable
  #14 = Utf8               print_info
  #15 = Utf8               ()V
  #16 = Utf8               SourceFile
  #17 = Utf8               Class2.java
  #18 = NameAndType        #10:#15        //  "<init>":()V
  #19 = NameAndType        #8:#9          //  info:Ljava/lang/String;
  #20 = Class              #27            //  java/lang/System
  #21 = NameAndType        #28:#29        //  out:Ljava/io/PrintStream;
  #22 = Class              #30            //  java/io/PrintStream
  #23 = NameAndType        #31:#11        //  println:(Ljava/lang/String;)V
  #24 = Utf8                /* not a comment */
  #25 = Utf8               Class2
  #26 = Utf8               java/lang/Object
  #27 = Utf8               java/lang/System
  #28 = Utf8               out
  #29 = Utf8               Ljava/io/PrintStream;
  #30 = Utf8               java/io/PrintStream
  #31 = Utf8               println
>>>>>>> 9852d261f5770e485a142b747224e91b3ac2926d
{
  java.lang.String info;
    flags: 

  public Class2(java.lang.String);
    flags: ACC_PUBLIC
    Code:
      stack=2, locals=2, args_size=2
         0: aload_0       
         1: invokespecial #1                  // Method java/lang/Object."<init>":()V
         4: aload_0       
         5: aload_1       
         6: putfield      #2                  // Field info:Ljava/lang/String;
         9: return        
      LineNumberTable:
        line 6: 0
        line 7: 4
        line 8: 9

  public void print_info();
    flags: ACC_PUBLIC
    Code:
      stack=2, locals=1, args_size=1
         0: getstatic     #3                  // Field java/lang/System.out:Ljava/io/PrintStream;
         3: aload_0       
         4: getfield      #2                  // Field info:Ljava/lang/String;
         7: invokevirtual #4                  // Method java/io/PrintStream.println:(Ljava/lang/String;)V
        10: getstatic     #3                  // Field java/lang/System.out:Ljava/io/PrintStream;
        13: ldc           #5                  // String  /* not a comment */
        15: invokevirtual #4                  // Method java/io/PrintStream.println:(Ljava/lang/String;)V
        18: return        
      LineNumberTable:
        line 11: 0
        line 12: 10
<<<<<<< HEAD
=======
        line 15: 18
>>>>>>> 9852d261f5770e485a142b747224e91b3ac2926d
}
